duplicaid/__init__.py
duplicaid/backup.py
duplicaid/cli.py
duplicaid/config.py
duplicaid/discovery.py
duplicaid/executor.py
duplicaid/local.py
duplicaid/ssh.py
duplicaid-4.3.0.dist-info/METADATA
duplicaid-4.3.0.dist-info/WHEEL
duplicaid-4.3.0.dist-info/entry_points.txt
duplicaid-4.3.0.dist-info/RECORD
